jobbergate_core/__init__.py
jobbergate_core/auth/__init__.py
jobbergate_core/auth/exceptions.py
jobbergate_core/auth/handler.py
jobbergate_core/auth/token.py
jobbergate_core/py.typed
jobbergate_core/sdk/__init__.py
jobbergate_core/sdk/clusters/__init__.py
jobbergate_core/sdk/clusters/app.py
jobbergate_core/sdk/clusters/schemas.py
jobbergate_core/sdk/constants.py
jobbergate_core/sdk/job_scripts/__init__.py
jobbergate_core/sdk/job_scripts/app.py
jobbergate_core/sdk/job_scripts/schemas.py
jobbergate_core/sdk/job_submissions/__init__.py
jobbergate_core/sdk/job_submissions/app.py
jobbergate_core/sdk/job_submissions/constants.py
jobbergate_core/sdk/job_submissions/schemas.py
jobbergate_core/sdk/job_templates/__init__.py
jobbergate_core/sdk/job_templates/app.py
jobbergate_core/sdk/job_templates/schemas.py
jobbergate_core/sdk/schemas.py
jobbergate_core/sdk/utils.py
jobbergate_core/tools/__init__.py
jobbergate_core/tools/requests.py
jobbergate_core/tools/sbatch.py
jobbergate_core/version.py
jobbergate_core-5.9.0.dist-info/LICENSE
jobbergate_core-5.9.0.dist-info/METADATA
jobbergate_core-5.9.0.dist-info/WHEEL
jobbergate_core-5.9.0.dist-info/RECORD
