Metadata-Version: 2.1
Name: jobbergate-core
Version: 5.9.0
Summary: Jobbergate Core
Home-page: https://github.com/omnivector-solutions/jobbergate
License: MIT
Author: Omnivector Solutions
Author-email: info@omnivector.solutions
Requires-Python: >=3.10,<4.0
Classifier: Development Status :: 5 - Production/Stable
Classifier: License :: OSI Approved :: MIT License
Classifier: Operating System :: OS Independent
Classifier: Programming Language :: Python :: 3
Classifier: Programming Language :: Python :: 3.10
Classifier: Programming Language :: Python :: 3.11
Classifier: Topic :: Scientific/Engineering
Requires-Dist: httpx (>=0.28.1,<0.29.0)
Requires-Dist: loguru (>=0.7.3,<0.8.0)
Requires-Dist: pendulum[test] (>=3.1.0,<4.0.0)
Requires-Dist: py-buzz (>=7.3.0,<8.0.0)
Requires-Dist: pydantic (>=2.12.5,<3.0.0)
Requires-Dist: python-jose (>=3.5.0,<4.0.0)
Project-URL: Bug Tracker, https://github.com/omnivector-solutions/jobbergate/issues
Project-URL: Changelog, https://github.com/omnivector-solutions/jobbergate/blob/main/jobbergate-core/CHANGELOG.rst
Project-URL: Repository, https://github.com/omnivector-solutions/jobbergate
